README
setup.py
encryptfs/__init__.py
encryptfs/cli.py
encryptfs/encrypt_files.py
encryptfs/encryptfs.py
encryptfs.egg-info/PKG-INFO
encryptfs.egg-info/SOURCES.txt
encryptfs.egg-info/dependency_links.txt
encryptfs.egg-info/entry_points.txt
encryptfs.egg-info/requires.txt
encryptfs.egg-info/top_level.txt