Metadata-Version: 1.0
Name: encryptfs
Version: 0.0.1
Summary: A simple file system that encrypts files individually.
Home-page: https://github.com/csu/encryptFS
Author: Christopher Su
Author-email: gh@christopher.su
License: UNKNOWN
Platform: UNKNOWN
